statuscast_api_pkg/StatusCastAPIDriver.py
statuscast_api_pkg/__init__.py
statuscast_api_pkg/__main__.py
statuscast_api_pkg/status_cofc_edu_job.py
statuscast_api_pkg/util.py
statuscast_api_pkg_huntaj-0.1.4.dist-info/LICENSE
statuscast_api_pkg_huntaj-0.1.4.dist-info/METADATA
statuscast_api_pkg_huntaj-0.1.4.dist-info/WHEEL
statuscast_api_pkg_huntaj-0.1.4.dist-info/top_level.txt
statuscast_api_pkg_huntaj-0.1.4.dist-info/RECORD
