Metadata-Version: 2.1
Name: statuscast-api-pkg-huntaj
Version: 0.1.4
Summary: Package for automating API calls to https://cofc.statuscast.com/api/v1
Home-page: https://hammond.cofc.edu/huntaj/statuscast_api_package
Author: Austin Hunt
Author-email: huntaj@cofc.edu
License: UNKNOWN
Platform: UNKNOWN
Classifier: Programming Language :: Python :: 3.6
Classifier: License :: OSI Approved :: MIT License
Classifier: Operating System :: OS Independent
Requires-Python: >=3.6
